Modules/Phylogenetic.py
Modules/Prediction.py
Modules/__init__.py
plasmidpermmm-0.1.data/scripts/plasmidperm
plasmidpermmm-0.1.data/scripts/plasmidpermm
plasmidpermmm-0.1.data/scripts/plasmidpermmm
plasmidpermmm-0.1.dist-info/LICENSE
plasmidpermmm-0.1.dist-info/METADATA
plasmidpermmm-0.1.dist-info/WHEEL
plasmidpermmm-0.1.dist-info/top_level.txt
plasmidpermmm-0.1.dist-info/RECORD
